dimclient/__init__.py
dimclient/version.py
dimclient-1.0.5.dist-info/METADATA
dimclient-1.0.5.dist-info/WHEEL
dimclient-1.0.5.dist-info/top_level.txt
dimclient-1.0.5.dist-info/RECORD
