Metadata-Version: 2.1
Name: dimclient
Version: 1.0.5
Summary: DNS and IP management Python library
Maintainer: zerimond
Project-URL: Homepage, https://github.com/ionos-cloud/dim
Project-URL: Issues, https://github.com/ionos-cloud/dim/issues
Classifier: Development Status :: 5 - Production/Stable
Classifier: Intended Audience :: Developers
Classifier: Programming Language :: Python :: 3
Classifier: License :: OSI Approved :: MIT License
Classifier: Operating System :: OS Independent
Requires-Python: >=3.6
